notion_pypi-1.0.0.dist-info/licenses/LICENSE
notionapi/__init__.py
notionapi/api_helper.py
notionapi/configuration.py
notionapi/notionapi_client.py
notionapi/controllers/__init__.py
notionapi/controllers/base_controller.py
notionapi/controllers/blocks_controller.py
notionapi/controllers/comments_controller.py
notionapi/controllers/databases_controller.py
notionapi/controllers/pages_controller.py
notionapi/controllers/search_controller.py
notionapi/controllers/users_controller.py
notionapi/exceptions/__init__.py
notionapi/exceptions/api_exception.py
notionapi/http/__init__.py
notionapi/http/http_call_back.py
notionapi/http/http_method_enum.py
notionapi/http/http_request.py
notionapi/http/http_response.py
notionapi/http/auth/__init__.py
notionapi/http/auth/o_auth_2.py
notionapi/models/__init__.py
notionapi/utilities/__init__.py
notionapi/utilities/file_wrapper.py
notion_pypi-1.0.0.dist-info/METADATA
notion_pypi-1.0.0.dist-info/WHEEL
notion_pypi-1.0.0.dist-info/top_level.txt
notion_pypi-1.0.0.dist-info/RECORD
