Metadata-Version: 2.4
Name: notion-pypi
Version: 1.0.0
Summary: Notion API is a REST API that enables programmatic access to Notion workspaces, allowing developers to create, read, update, and manage databases, pages, blocks, users, and comments through authenticated endpoints. It provides comprehensive functionality for querying databases, managing page content, and searching across shared workspaces 
Author-email: Muhammad Hamza Shahzad <muhammad.hamza@apimatic.io>
Project-URL: Documentation, https://docs.apimatic.io/
Requires-Python: >=3.7
License-File: LICENSE
Requires-Dist: apimatic-core>=0.2.20,~=0.2.0
Requires-Dist: apimatic-core-interfaces>=0.1.5,~=0.1.0
Requires-Dist: apimatic-requests-client-adapter>=0.1.6,~=0.1.0
Provides-Extra: testutils
Requires-Dist: pytest>=7.2.2; extra == "testutils"
Dynamic: license-file
